basically_ti_basic/__init__.py
basically_ti_basic/__version__.py
basically_ti_basic/main.py
basically_ti_basic/compiler/__init__.py
basically_ti_basic/files/__init__.py
basically_ti_basic/tokens/__init__.py
basically_ti_basic-0.1.7.dist-info/LICENSE
basically_ti_basic-0.1.7.dist-info/METADATA
basically_ti_basic-0.1.7.dist-info/WHEEL
basically_ti_basic-0.1.7.dist-info/entry_points.txt
basically_ti_basic-0.1.7.dist-info/top_level.txt
basically_ti_basic-0.1.7.dist-info/RECORD
