Metadata-Version: 2.1
Name: basically-ti-basic
Version: 0.1.7
Summary: Package to decompile and recompile .8Xp files from the TI-83/TI-84 calculators.
Home-page: https://github.com/TabulateJarl8/basically-ti-basic
Author: Tabulate
Author-email: tabulatejarl8@gmail.com
License: UNKNOWN
Platform: UNKNOWN
Classifier: Programming Language :: Python :: 3
Classifier: License :: OSI Approved :: MIT License
Classifier: Operating System :: OS Independent
Requires-Python: >=3.6
License-File: LICENSE
